shopsavvy/__init__.py
shopsavvy/client.py
shopsavvy/exceptions.py
shopsavvy/models.py
shopsavvy_sdk-1.0.3.dist-info/METADATA
shopsavvy_sdk-1.0.3.dist-info/WHEEL
shopsavvy_sdk-1.0.3.dist-info/top_level.txt
shopsavvy_sdk-1.0.3.dist-info/RECORD
