Metadata-Version: 2.4
Name: shopsavvy-sdk
Version: 1.0.3
Summary: Official Python SDK for ShopSavvy Data API - Access product data, pricing, and price history
Author: ShopSavvy by Monolith Technologies, Inc.
Maintainer: ShopSavvy by Monolith Technologies, Inc.
Project-URL: Homepage, https://shopsavvy.com/data
Project-URL: Documentation, https://shopsavvy.com/data/documentation
Project-URL: Repository, https://github.com/shopsavvy/sdk-python
Project-URL: Bug Tracker, https://github.com/shopsavvy/sdk-python/issues
Keywords: shopsavvy,product-data,pricing,e-commerce,shopping,price-comparison,retail,api-client,python
Classifier: Development Status :: 5 - Production/Stable
Classifier: Intended Audience :: Developers
Classifier: Operating System :: OS Independent
Classifier: Programming Language :: Python :: 3
Classifier: Programming Language :: Python :: 3.8
Classifier: Programming Language :: Python :: 3.9
Classifier: Programming Language :: Python :: 3.10
Classifier: Programming Language :: Python :: 3.11
Classifier: Programming Language :: Python :: 3.12
Classifier: Topic :: Software Development :: Libraries :: Python Modules
Classifier: Topic :: Internet :: WWW/HTTP :: Dynamic Content
Classifier: Topic :: Office/Business :: Financial
Requires-Python: >=3.8
Requires-Dist: httpx>=0.24.0
Requires-Dist: pydantic>=2.0.0
Requires-Dist: typing-extensions>=4.0.0
Provides-Extra: dev
Requires-Dist: pytest>=7.0.0; extra == "dev"
Requires-Dist: pytest-asyncio>=0.21.0; extra == "dev"
Requires-Dist: pytest-cov>=4.0.0; extra == "dev"
Requires-Dist: black>=23.0.0; extra == "dev"
Requires-Dist: isort>=5.12.0; extra == "dev"
Requires-Dist: mypy>=1.0.0; extra == "dev"
Requires-Dist: flake8>=6.0.0; extra == "dev"
Requires-Dist: httpx-mock>=0.11.0; extra == "dev"
